original_sdk/__init__.py
original_sdk/__pkg__.py
original_sdk/async_client.py
original_sdk/client.py
original_sdk/utils.py
original_sdk/base/__init__.py
original_sdk/base/client.py
original_sdk/types/__init__.py
original_sdk/types/environment.py
original_sdk/types/exceptions.py
original_sdk/types/original_response.py
original_sdk/types/rate_limit.py
original_sdk-1.4.1.dist-info/LICENSE
original_sdk-1.4.1.dist-info/METADATA
original_sdk-1.4.1.dist-info/WHEEL
original_sdk-1.4.1.dist-info/top_level.txt
original_sdk-1.4.1.dist-info/RECORD
