Metadata-Version: 2.1
Name: original-sdk
Version: 1.4.1
Summary: Python client for Original.
Home-page: https://github.com/GetOriginal/original-python
Author: Alexander Turowicz
Author-email: support@getoriginal.com
Classifier: Intended Audience :: Developers
Classifier: Intended Audience :: System Administrators
Classifier: Operating System :: OS Independent
Classifier: Topic :: Software Development
Classifier: Development Status :: 5 - Production/Stable
Classifier: Natural Language :: English
Classifier: Programming Language :: Python :: 3
Classifier: Programming Language :: Python :: 3.7
Classifier: Programming Language :: Python :: 3.8
Classifier: Programming Language :: Python :: 3.9
Classifier: Programming Language :: Python :: 3.10
Classifier: Topic :: Software Development :: Libraries :: Python Modules
Requires-Python: >=3.7
License-File: LICENSE
Requires-Dist: requests (<3,>=2.22.0)
Requires-Dist: aiodns (>=2.0.0)
Requires-Dist: aiohttp (<4,>=3.6.0)
Requires-Dist: aiofile (<4,>=3.1)
Requires-Dist: pyjwt (<3,>=2.0.0)
Requires-Dist: typing-extensions ; python_version < "3.8"
Provides-Extra: ci
Requires-Dist: black ; extra == 'ci'
Requires-Dist: flake8 ; extra == 'ci'
Requires-Dist: flake8-isort ; extra == 'ci'
Requires-Dist: flake8-bugbear ; extra == 'ci'
Requires-Dist: pytest-cov ; extra == 'ci'
Requires-Dist: mypy ; extra == 'ci'
Requires-Dist: types-requests ; extra == 'ci'
Provides-Extra: test
Requires-Dist: globals ; extra == 'test'
Requires-Dist: pytest (<=8.1.1) ; extra == 'test'
Requires-Dist: pytest-asyncio (<=0.21.1) ; extra == 'test'
Requires-Dist: python-dotenv ; extra == 'test'
